mne_faster/__init__.py
mne_faster/faster.py
mne_faster-1.2.1.dist-info/LICENSE
mne_faster-1.2.1.dist-info/METADATA
mne_faster-1.2.1.dist-info/WHEEL
mne_faster-1.2.1.dist-info/top_level.txt
mne_faster-1.2.1.dist-info/RECORD
