Metadata-Version: 2.2
Name: mne-faster
Version: 1.2.1
Summary: MNE-FASTER: automatic bad channel/epoch/component detection
Author-email: Marijn van Vliet <w.m.vanvliet@gmail.com>
License: BSD-3-Clause
Project-URL: Bug Tracker, https://github.com/wmvanvliet/mne-faster/issues/
Project-URL: Source Code, https://github.com/wmvanvliet/mne-faster
Keywords: rsa,meg,eeg,neuroimaging,mne-python
Classifier: Intended Audience :: Science/Research
Classifier: Intended Audience :: Developers
Classifier: License :: OSI Approved
Classifier: Programming Language :: Python
Classifier: Topic :: Software Development
Classifier: Topic :: Scientific/Engineering
Classifier: Operating System :: Microsoft :: Windows
Classifier: Operating System :: POSIX
Classifier: Operating System :: Unix
Classifier: Operating System :: MacOS
Requires-Python: >=3.9
License-File: LICENSE
Requires-Dist: mne
